logstruct/__init__.py
logstruct/_constants.py
logstruct/_context.py
logstruct/_formatters.py
logstruct/_logger.py
logstruct/_version.py
logstruct/py.typed
logstruct-0.2.1.dist-info/licenses/LICENCE
logstruct-0.2.1.dist-info/METADATA
logstruct-0.2.1.dist-info/WHEEL
logstruct-0.2.1.dist-info/top_level.txt
logstruct-0.2.1.dist-info/RECORD
