Metadata-Version: 2.4
Name: logstruct
Version: 0.2.1
Summary: Structured stdlib logging with context vars
Author-email: Karoline Pauls <code@karolinepauls.com>
License: BSD-3-Clause
Project-URL: Source, https://gitlab.com/karolinepauls/logstruct
Project-URL: Documentation, https://logstruct.readthedocs.io/
Project-URL: Changelog, https://gitlab.com/karolinepauls/logstruct/-/blob/master/CHANGELOG.rst
Keywords: logging,log,logger,structured,structure,json,stdlib,structlog
Classifier: Programming Language :: Python :: 3
Classifier: Development Status :: 4 - Beta
Classifier: Intended Audience :: Developers
Classifier: Topic :: System :: Logging
Classifier: Typing :: Typed
Requires-Python: >=3.9
License-File: LICENCE
Dynamic: license-file
